CHANGELOG.txt
MANIFEST.in
README.txt
setup.py
pycrsltd/__init__.py
pycrsltd/bits.py
pycrsltd/colorcal.py
pycrsltd/optical.py
pycrsltd/shaders.py
pycrsltd.egg-info/PKG-INFO
pycrsltd.egg-info/SOURCES.txt
pycrsltd.egg-info/dependency_links.txt
pycrsltd.egg-info/top_level.txt
pycrsltd/tests/testCALdevices.py
pycrsltd/tests/testColorMode.py