Metadata-Version: 1.0
Name: pycrsltd
Version: 0.1
Summary: A Python library to interface with CRS Ltd hardware
Home-page: https://github.com/crsltd-opensource/pycrsltd
Author: Jon Peirce
Author-email: jon@peirce.org.uk
License: MIT
Download-URL: https://github.com/crsltd-opensource/pycrsltd/downloads
Platform: UNKNOWN
Classifier: Development Status :: 3 - Alpha
Classifier: Operating System :: MacOS :: MacOS X
Classifier: Operating System :: Microsoft :: Windows
Classifier: Operating System :: POSIX
Classifier: License :: OSI Approved :: MIT License
Classifier: Programming Language :: Python
